karellen/clang_build_ext/__init__.py
clang_build_ext-0.0.2.dist-info/METADATA
clang_build_ext-0.0.2.dist-info/WHEEL
clang_build_ext-0.0.2.dist-info/entry_points.txt
clang_build_ext-0.0.2.dist-info/namespace_packages.txt
clang_build_ext-0.0.2.dist-info/top_level.txt
clang_build_ext-0.0.2.dist-info/zip-safe
clang_build_ext-0.0.2.dist-info/RECORD
