Metadata-Version: 2.1
Name: clang_build_ext
Version: 0.0.2
Summary: Clang-based extension builder
Home-page: https://github.com/karellen/clang-build-ext
Author: Karellen, Inc.
Author-email: supervisor@karellen.co
Maintainer: Arcadiy Ivanov
Maintainer-email: arcadiy@karellen.co
License: Apache License, Version 2.0
Project-URL: Bug Tracker, https://github.com/karellen/clang-build-ext/issues
Project-URL: Documentation, https://github.com/karellen/clang-build-ext/
Project-URL: Source Code, https://github.com/karellen/clang-build-ext/
Keywords: setuptools extension cpythonclang c cpp cxx c++ compile
Classifier: License :: OSI Approved :: Apache Software License
Classifier: Programming Language :: Python :: 3
Classifier: Operating System :: POSIX :: Linux
Classifier: Topic :: System :: Archiving :: Packaging
Classifier: Topic :: Software Development :: Build Tools
Classifier: Intended Audience :: Developers
Classifier: Development Status :: 4 - Beta
Requires-Python: >=3.7
